translator_uabthehack/__init__.py
translator_uabthehack/main.py
translator_uabthehack/traductor.py
translator_uabthehack/variable_seeker.py
translator_uabthehack-0.4.0.dist-info/METADATA
translator_uabthehack-0.4.0.dist-info/WHEEL
translator_uabthehack-0.4.0.dist-info/RECORD
