Metadata-Version: 2.1
Name: translator-uabthehack
Version: 0.4.0
Summary: 
Author: Noobie's lab
Author-email: lluc@vivet.cat
Requires-Python: >=3.12,<4.0
Classifier: Programming Language :: Python :: 3
Classifier: Programming Language :: Python :: 3.12
Requires-Dist: deep-translator (>=1.11.4,<2.0.0)
